README.txt
setup.cfg
setup.py
docs/HISTORY.txt
haufe/__init__.py
haufe.monitoring.egg-info/PKG-INFO
haufe.monitoring.egg-info/SOURCES.txt
haufe.monitoring.egg-info/dependency_links.txt
haufe.monitoring.egg-info/entry_points.txt
haufe.monitoring.egg-info/namespace_packages.txt
haufe.monitoring.egg-info/not-zip-safe
haufe.monitoring.egg-info/requires.txt
haufe.monitoring.egg-info/top_level.txt
haufe/monitoring/__init__.py
haufe/monitoring/config.py
haufe/monitoring/configure.zcml
haufe/monitoring/controlpanel.py
haufe/monitoring/gil_monitor.py
haufe/monitoring/header.txt
haufe/monitoring/network.py
haufe/monitoring/permissions.zcml
haufe/monitoring/browser/__init__.py
haufe/monitoring/browser/configure.zcml
haufe/monitoring/browser/error_log_view.pt
haufe/monitoring/browser/error_log_view.py
haufe/monitoring/browser/monitor.pt
haufe/monitoring/browser/monitor.py
haufe/monitoring/browser/status.py
haufe/monitoring/browser/unix.py
haufe/monitoring/resources/close.png
haufe/monitoring/resources/jquery.tools.min.js
haufe/monitoring/resources/styles.css