Metadata-Version: 1.0
Name: haufe.monitoring
Version: 0.2.1.1
Summary: Zope 2 ZEO Client Watch
Home-page: UNKNOWN
Author: Andreas Jung
Author-email: info@zopyx.com
License: ZPL
Platform: UNKNOWN
Classifier: Programming Language :: Python
Classifier: Topic :: Software Development :: Libraries :: Python Modules
Classifier: Framework :: Zope2
Classifier: Topic :: System :: Monitoring
